{
    "hash": "83dca9eb05483da901d60d876c1eb9e6e5f6364330f1fe7e664cbcb57cc337f7",
    "timestamp": "2025-11-27T09:45:50.174870Z",
    "source_type": "text",
    "filename": null,
    "raw_text": "Neural network AI algorithm implementation",
    "score": 1781.0,
    "value": 18810.0,
    "value_formatted": "$18.81K",
    "vector": {
        "x": 0.220662,
        "y": 0.683524,
        "z": 0.535452
    },
    "analysis": {
        "word_count": 5,
        "char_count": 42,
        "keyword_matches": {
            "neural": {
                "count": 1,
                "bonus": 450
            },
            "ai": {
                "count": 1,
                "bonus": 150
            },
            "algorithm": {
                "count": 1,
                "bonus": 150
            }
        },
        "depth_bonus": 0,
        "complexity_bonus": 1000
    }
}